solsticepy/__init__.py
solsticepy/aiming_strategy.py
solsticepy/cal_field.py
solsticepy/cal_layout.py
solsticepy/cal_sun.py
solsticepy/data_spectral.py
solsticepy/find_solstice.py
solsticepy/gen_vtk.py
solsticepy/gen_yaml.py
solsticepy/process_raw.py
solsticepy_pkg_jdpipe-0.1.5.dist-info/LICENSE
solsticepy_pkg_jdpipe-0.1.5.dist-info/METADATA
solsticepy_pkg_jdpipe-0.1.5.dist-info/WHEEL
solsticepy_pkg_jdpipe-0.1.5.dist-info/top_level.txt
solsticepy_pkg_jdpipe-0.1.5.dist-info/RECORD
