Metadata-Version: 2.1
Name: solsticepy-pkg-jdpipe
Version: 0.1.5
Summary: Scripts and wrappers for Solstice ray-tracing software
Home-page: https://github.com/anustg/solstice-scripts
Author: Ye Wang
Author-email: ye.wang@anu.edu.au
License: GPL v3.0 or later, see LICENSE file
Platform: UNKNOWN
Classifier: Development Status :: 4 - Beta
Classifier: Environment :: Console
Classifier: Intended Audience :: Science/Research
Classifier: License :: OSI Approved :: GNU General Public License v3 or later (GPLv3+)
Classifier: Natural Language :: English
Classifier: Operating System :: Microsoft :: Windows :: Windows 10
Classifier: Operating System :: POSIX :: Linux
Classifier: Programming Language :: Python :: 2
Classifier: Programming Language :: Python :: 3
Classifier: Topic :: Scientific/Engineering :: Physics
Requires-Python: >=2.7
Requires-Dist: scipy
Requires-Dist: numpy
Requires-Dist: uncertainties
